README.rst
setup.cfg
setup.py
bcwallet/__init__.py
bcwallet/bc_utils.py
bcwallet/bcwallet.py
bcwallet/cl_utils.py
bcwallet/version_checker.py
bcwallet.egg-info/PKG-INFO
bcwallet.egg-info/SOURCES.txt
bcwallet.egg-info/dependency_links.txt
bcwallet.egg-info/entry_points.txt
bcwallet.egg-info/requires.txt
bcwallet.egg-info/top_level.txt