Metadata-Version: 1.0
Name: bcwallet
Version: 1.2.7
Summary: Simple BIP32 HD cryptocurrecy command line wallet
Home-page: https://github.com/blockcypher/bcwallet/
Author: Michael Flaxman
Author-email: mflaxman+blockcypher@gmail.com
License: UNKNOWN
Platform: UNKNOWN
